<Properties StartupConfiguration="{41C224D6-6C5E-4613-A9DA-51785E6EE8EA}|Default">
  <MonoDevelop.Ide.Workbench ActiveDocument="API/Program.cs">
    <Files>
      <File FileName="../../SpaceNav/Assets/scripts/planetInfo.cs" Line="12" Column="1" />
      <File FileName="API/Program.cs" Line="113" Column="14" />
    </Files>
    <Pads>
      <Pad Id="ProjectPad">
        <State name="__root__">
          <Node name="API" expanded="True">
            <Node name="API" expanded="True">
              <Node name="Program.cs" selected="True" />
            </Node>
          </Node>
        </State>
      </Pad>
    </Pads>
  </MonoDevelop.Ide.Workbench>
  <MonoDevelop.Ide.ItemProperties.API FirstBuild="True" PreferredExecutionTarget="MonoDevelop.Default" />
  <MonoDevelop.Ide.DebuggingService.PinnedWatches />
  <MonoDevelop.Ide.Workspace ActiveConfiguration="Debug|anycpu" />
  <MonoDevelop.Ide.DebuggingService.Breakpoints>
    <BreakpointStore />
  </MonoDevelop.Ide.DebuggingService.Breakpoints>
  <MultiItemStartupConfigurations />
</Properties>